sixty_nuts/__init__.py
sixty_nuts/cli.py
sixty_nuts/crypto.py
sixty_nuts/events.py
sixty_nuts/lnurl.py
sixty_nuts/mint.py
sixty_nuts/py.typed
sixty_nuts/relay.py
sixty_nuts/temp.py
sixty_nuts/types.py
sixty_nuts/wallet.py
sixty_nuts-0.1.3.dist-info/METADATA
sixty_nuts-0.1.3.dist-info/WHEEL
sixty_nuts-0.1.3.dist-info/entry_points.txt
sixty_nuts-0.1.3.dist-info/licenses/LICENSE
sixty_nuts-0.1.3.dist-info/RECORD
