Metadata-Version: 2.4
Name: sixty-nuts
Version: 0.1.3
Summary: Sixty Nuts - NIP-60 Cashu Wallet Implementation
Project-URL: Repository, https://github.com/shroominic/sixty-nuts
Author-email: shroominic <contact@shroominic.com>
License: MIT
License-File: LICENSE
Keywords: bitcoin,cashu,ecash,lightning,nip-60,nostr,wallet
Classifier: Development Status :: 3 - Alpha
Classifier: Intended Audience :: Developers
Classifier: License :: OSI Approved :: MIT License
Classifier: Programming Language :: Python :: 3
Classifier: Programming Language :: Python :: 3.11
Classifier: Programming Language :: Python :: 3.12
Classifier: Programming Language :: Python :: 3.13
Classifier: Topic :: Office/Business :: Financial
Classifier: Topic :: Security :: Cryptography
Classifier: Topic :: Software Development :: Libraries :: Python Modules
Requires-Python: >=3.11
Requires-Dist: bech32>=1.2.0
Requires-Dist: cbor2>=5.6.5
Requires-Dist: coincurve>=21.0.0
Requires-Dist: cryptography>=45.0.3
Requires-Dist: httpx>=0.28.1
Requires-Dist: typer>=0.16.0
Requires-Dist: websockets>=15.0.1
Provides-Extra: qr
Requires-Dist: qrcode>=8.0; extra == 'qr'
